BinanceTrApi/Apihelpers.py
BinanceTrApi/BinanceTrRequests.py
BinanceTrApi/BinanceTrService.py
BinanceTrApi/TimeModel.py
BinanceTrApi/UserModel.py
BinanceTrApi/__init__.py
BinanceTrApi/constants.json
BinanceTrApi-0.1.1.dist-info/LICENSE
BinanceTrApi-0.1.1.dist-info/METADATA
BinanceTrApi-0.1.1.dist-info/WHEEL
BinanceTrApi-0.1.1.dist-info/top_level.txt
BinanceTrApi-0.1.1.dist-info/RECORD
