Metadata-Version: 2.1
Name: BinanceTrApi
Version: 0.1.1
Summary: TRbinance API implementation in python.
Home-page: UNKNOWN
Author: Futuristic Exchanger
Author-email: futuristic.exchanger@gmail.com
License: UNKNOWN
Platform: UNKNOWN
Classifier: Programming Language :: Python :: 3
Classifier: License :: OSI Approved :: MIT License
Classifier: Operating System :: OS Independent
Requires-Python: >=3.6
